Metadata-Version: 1.2
Name: manga-py.img2pdf
Version: 2.0.4
Summary: Universal assistant download manga.
Home-page: https://github.com/manga-py/img2pdf
Author: Sergey Zharkov
Author-email: sttv-pc@mail.ru
License: MIT
Download-URL: https://github.com/manga-py/img2pdf/archive/2.0.4.tar.gz
Keywords: manga-downloader,manga,manga-py
Platform: UNKNOWN
Classifier: Development Status :: 5 - Production/Stable
Classifier: License :: OSI Approved :: MIT License
Classifier: Natural Language :: English
Classifier: Environment :: Console
Classifier: Programming Language :: Python :: 3.6
Classifier: Programming Language :: Python :: 3.7
Classifier: Programming Language :: Python :: 3.8
Classifier: Topic :: Internet :: WWW/HTTP
Requires-Python: >=3.6
